terrachicken/__init__.py
terrachicken/functions/__init__.py
terrachicken/functions/github_functions.py
terrachicken/functions/tfc_functions.py
terrachicken/main.py
terrachicken/src/__init__.py
terrachicken/src/create.py
terrachicken/src/delete.py
terrachicken/src/list.py
terrachicken/templates/terraform_block.jinja2
terrachicken/utils/__init__.py
terrachicken/utils/pretty.py
terrachicken-0.1.1.dist-info/entry_points.txt
terrachicken-0.1.1.dist-info/WHEEL
terrachicken-0.1.1.dist-info/METADATA
terrachicken-0.1.1.dist-info/RECORD
