Metadata-Version: 2.1
Name: terrachicken
Version: 0.1.1
Summary: CLI Tool to configure Terraform Cloud Workspaces and Git Repos
Home-page: https://github.com/Thaley17/TerraChicken
Author: Thaley17
Author-email: tyler.haley.17@outlook.com
Requires-Python: >=3.9,<4.0
Classifier: Programming Language :: Python :: 3
Classifier: Programming Language :: Python :: 3.10
Classifier: Programming Language :: Python :: 3.9
Requires-Dist: Jinja2 (==3.0.3)
Requires-Dist: PyGithub (==1.55)
Requires-Dist: python-dotenv (==0.19.2)
Requires-Dist: terrasnek (==0.1.9)
Requires-Dist: typer (==0.3.2)
Project-URL: Repository, https://github.com/Thaley17/TerraChicken
